bogrod/VERSION
bogrod/__init__.py
bogrod/__main__.py
bogrod/controller.py
bogrod/sbom.py
bogrod/settings.py
bogrod/util.py
bogrod/vexfile.py
bogrod/contrib/__init__.py
bogrod/contrib/aggregator.py
bogrod/contrib/dummy.py
bogrod/contrib/elementaris.py
bogrod/resources/bom-1.4.schema.json
bogrod/resources/bom-1.5.schema.json
bogrod/resources/vex-1.0.schema.json
bogrod/tests/__init__.py
bogrod/tests/test_bogrod.py
bogrod/tests/test_tui.py
bogrod/tui/__init__.py
bogrod/tui/app.py
bogrod/tui/editor.tcss
bogrod/tui/styles.tcss
bogrod/tui/vexedit.py
bogrod/tui/vulnlist.py
bogrod/tui/widgets/__init__.py
bogrod/tui/widgets/modals.py
bogrod/tui/widgets/multitable.py
bogrod/tui/widgets/radioslist.py
resources/process.drawio
resources/process.png
bogrod-0.4.3.dist-info/LICENSE
bogrod-0.4.3.dist-info/METADATA
bogrod-0.4.3.dist-info/WHEEL
bogrod-0.4.3.dist-info/entry_points.txt
bogrod-0.4.3.dist-info/top_level.txt
bogrod-0.4.3.dist-info/RECORD
