Metadata-Version: 2.1
Name: bogrod
Version: 0.4.3
Summary: Manage SBOM, VEX records and release notes in a single tool
Home-page: https://github.com/productaize/bogrod
Author: Patrick Senti
Author-email: patrick@productaize.io
License: MIT
License-File: LICENSE
Requires-Dist: jsonschema<4
Requires-Dist: pyyaml
Requires-Dist: tabulate
Requires-Dist: attrdict
Requires-Dist: textual
Requires-Dist: textual-dev
Requires-Dist: requests
Requires-Dist: yaspin
Requires-Dist: keyring
Provides-Extra: dev
Requires-Dist: tox; extra == "dev"
Requires-Dist: pytest; extra == "dev"
Requires-Dist: build; extra == "dev"
Requires-Dist: pytest-textual-snapshot; extra == "dev"
